polypart/__init__.py
polypart/arrangements.py
polypart/delres.py
polypart/ftyping.py
polypart/geometry.py
polypart/inc_enu.py
polypart/io.py
polypart/lp_backends.py
polypart/moduli.py
polypart/polytopes.py
polypart/ppart.py
polypart/utils.py
polypart/volume.py
polypart-0.2.0.dist-info/licenses/LICENSE
polypart-0.2.0.dist-info/METADATA
polypart-0.2.0.dist-info/WHEEL
polypart-0.2.0.dist-info/top_level.txt
polypart-0.2.0.dist-info/RECORD
