Metadata-Version: 2.4
Name: polypart
Version: 0.2.0
Summary: Robust polytope partitioning and efficient point classification in Python
Author-email: Sergio Herreros Pérez <sergio.herreros@alu.icai.comillas.edu>, David Alfaya Sánchez <dalfaya@icai.comillas.edu>, Jaime Pizarroso Gonzalo <jpizarroso@comillas.edu>
License-Expression: MIT
Project-URL: Repository, https://github.com/CIAMOD/polypart
Project-URL: Changelog, https://github.com/CIAMOD/polypart/blob/master/CHANGELOG.md
Keywords: polytope,partition,hyperplane arrangement,point location,decision tree
Classifier: Development Status :: 4 - Beta
Classifier: Intended Audience :: Developers
Classifier: Intended Audience :: Science/Research
Classifier: Programming Language :: Python :: 3.10
Classifier: Programming Language :: Python :: 3.11
Classifier: Topic :: Scientific/Engineering
Classifier: Topic :: Software Development :: Libraries
Requires-Python: >=3.10
License-File: LICENSE
Requires-Dist: gmpy2==2.2.2a1
Requires-Dist: ipykernel>=7.1.0
Requires-Dist: matplotlib>=3.10.7
Requires-Dist: numpy>=1.24.4
Requires-Dist: psutil>=7.1.3
Requires-Dist: pycddlib>=3.0.2
Requires-Dist: resource>=0.2.1
Requires-Dist: tqdm>=4.67.1
Dynamic: license-file
